bgtunnel.py
bgtunnel-0.4.1.dist-info/DESCRIPTION.rst
bgtunnel-0.4.1.dist-info/METADATA
bgtunnel-0.4.1.dist-info/RECORD
bgtunnel-0.4.1.dist-info/WHEEL
bgtunnel-0.4.1.dist-info/entry_points.txt
bgtunnel-0.4.1.dist-info/metadata.json
bgtunnel-0.4.1.dist-info/pbr.json
bgtunnel-0.4.1.dist-info/top_level.txt
