Metadata-Version: 2.0
Name: bgtunnel
Version: 0.4.1
Summary: Initiate SSH tunnels in the background
Home-page: https://github.com/jmagnusson/bgtunnel
Author: Jacob Magnusson
Author-email: m@jacobian.se
License: BSD
Platform: unix
Platform: macos
Classifier: Development Status :: 3 - Alpha
Classifier: Intended Audience :: Developers
Classifier: License :: OSI Approved :: BSD License
Classifier: Operating System :: Unix
Classifier: Programming Language :: Python
